egrader/__init__.py
egrader/assess.py
egrader/cli_bin.py
egrader/cli_lib.py
egrader/fetch.py
egrader/git.py
egrader/paths.py
egrader/plugin.py
egrader/report.py
egrader/types.py
egrader/yaml.py
egrader/plugins/__init__.py
egrader/plugins/helpers.py
egrader/plugins/inter_repo.py
egrader/plugins/repo.py
egrader/plugins/report.py
egrader-0.0.10.dist-info/licenses/LICENSE
egrader-0.0.10.dist-info/METADATA
egrader-0.0.10.dist-info/WHEEL
egrader-0.0.10.dist-info/entry_points.txt
egrader-0.0.10.dist-info/top_level.txt
egrader-0.0.10.dist-info/RECORD
